pyavaccess/__init__.py
pyavaccess/avaccess_serial.py
pyavaccess/hdmi_matrix.py
pyavaccess/config/matrix_devices.py
pyavaccess-0.2.0.dist-info/METADATA
pyavaccess-0.2.0.dist-info/WHEEL
pyavaccess-0.2.0.dist-info/licenses/LICENSE
pyavaccess-0.2.0.dist-info/RECORD
