Metadata-Version: 2.3
Name: pyavaccess
Version: 0.2.0
Summary: Automation library for AV Access devices
Project-URL: Source Code, https://github.com/latelylk/pyavaccess
Project-URL: Bug Reports, https://github.com/latelylk/pyavaccess/issues
License: GPLv3+
License-File: LICENSE
Classifier: Development Status :: 4 - Beta
Classifier: License :: OSI Approved :: GNU General Public License v3 (GPLv3)
Classifier: Operating System :: OS Independent
Classifier: Programming Language :: Python :: 3
Requires-Python: >=3.8
Requires-Dist: pyserial>=3.5
